{
  "meta": [
    {
      "job_title": "Fixed Income Trader",
      "job_category": "Finance",
      "job_class": "Trader",
      "sector": "Investment Management",
      "salary": 120000,
      "remote": false
    }
  ],
  "skills": [
    {
      "skill": "Portfolio Investing",
      "experience": 5
    },
    {
      "skill": "Trade Order Management",
      "experience": 5
    },
    {
      "skill": "Investment Strategy",
      "experience": 5
    },
    {
      "skill": "Financial Analysis",
      "experience": 5
    },
    {
      "skill": "Microsoft Word and Excel",
      "experience": 5
    },
    {
      "skill": "Bloomberg",
      "experience": 5
    },
    {
      "skill": "Electronic Trading Platforms",
      " experience": 5
    },
    {
      "skill": "Telephone Techniques",
      " experience": 5
    },
    {
      "skill": "Policies and Procedures Interpretation",
      "experience": 5
    },
    {
      "skill": "Organizational Skills",
      "experience": 5
    },
    {
      "skill": "Time Management",
      "experience": 5
    },
    {
      "skill": "Communication Skills",
      "experience": 5
    },
    {
      "skill": "Analytical Skills",
      "experience": 5
    },
    {
      "skill": "Self-Motivation",
      "experience": 5
    },
    {
      "skill": "Problem-Solving",
      "experience": 5
    },
    {
      "skill": "Teamwork",
      "experience": 5
    }
  ],
  "duties_responsibilities": [
    {
      "duty": "Perform trading functions in equity and fixed income securities."
    },
    {
      "duty": "Build and generate trading reports for management and compliance."
    },
    {
      "duty": "Research investment opportunities and assist with ongoing surveillance of bond issuer credit quality."
    },
    {
      "duty": "Assist with the development of investment strategy for fixed income portfolios, including research and implementation of investment opportunities."
    },
    {
      "duty": "Manage trading error process including written summary, adjustments to client and firm accounts, as well as reporting to investment committee."
    },
    {
      "duty": "Serve as a backup to other traders."
    }
  ],
  "subjective_elements": [
    {
      "soldier_general": 100,
      "student_teacher": 80,
      "introvert_extrovert": 120
    }
  ],
  "education_certification": [
    {
      "credential": "Undergraduate degree in related field; Experience may replace education requirement. Three to five years of securities industry experience. Preferred experience in fixed income. Previous trading experience required. FINRA Series 7 securities license required or be willing to obtain within the first year."
    }
  ]
}