{
  "meta": [
    {
      "job_title": "Resourcing Analyst",
      "job_category": "Consulting",
      "job_class": "Analyst",
      "sector": "Consulting",
      "salary": 75000,
      "remote": true
    }
  ],
  "skills": [
    {
      "skill": "Data Analysis",
      "experience": 5
    },
    {
      "skill": "Advanced Excel Skills",
      "experience": 5
    },
    {
      "skill": "Operational Analysis",
      "experience": 5
    },
    {
      "skill": "Communication Skills",
      "experience": 5
    },
    {
      "skill": "Problem-Solving",
      "experience": 5
    },
    {
      "skill": "Microsoft Office",
      "experience": 5
    },
    {
      "skill": "Analytical Skills",
      "experience": 5
    },
    {
      "skill": "Organizational Skills",
      "experience": 5
    },
    {
      "skill": "Collaborative Skills",
      "experience": 5
    }
  ],
  "duties_responsibilities": [
    {
      "duty": "Staffing all necessary resource requests for the Consulting organization."
    },
    {
      "duty": "Partnering with Delivery Managers and Operation Analysts to staff the scheduled projects."
    },
    {
      "duty": "Collaborating with project managers and consultants on scheduling projects."
    },
    {
      "duty": "Managing the resourcing request queue and reviewing statements of work."
    },
    {
      "duty": "Identifying over or underutilized associates and highlighting future conflicting events."
    },
    {
      "duty": "Working on scheduling and troubleshooting project schedules."
    }
  ],
  "subjective_elements": [
    {
      "soldier_general": 100,
      "student_teacher": 85,
      "introvert_extrovert": 90
    }
  ],
  "education_certification": [
    {
      "credential": "Bachelor's degree or equivalent relevant work experience"
    }
  ]
}