{
  "meta": [
    {
      "job_title": "Audio Producer",
      "job_category": "Creative",
      "job_class": "Producer",
      "sector": "Creative",
      "salary": 28,
      "remote": false
    }
  ],
  "skills": [
    {
      "skill": "Audio Production",
      "experience": 3
    },
    {
      "skill": "Research",
      "experience": 3
    },
    {
      "skill": "Collaboration",
      "experience": 3
    },
    {
      "skill": "Program Development",
      "experience": 3
    },
    {
      "skill": "Content Creation",
      "experience": 3
    },
    {
      "skill": "Communication Skills",
      "experience": 3
    },
    {
      "skill": "Script Writing",
      "experience": 3
    }
  ],
  "duties_responsibilities": [
    {
      "duty": "Research, produce, and oversee new audio programs, including for daily FOF radio broadcast."
    },
    {
      "duty": "Contribute to the creative process and collaborate with hosts and voice talent to create engaging audio content."
    },
    {
      "duty": "Collaborate with web and marketing teams to provide content for associated web pages and promotional materials."
    },
    {
      "duty": "Conduct in-depth research on various topics to gather relevant information and insights for program development."
    },
    {
      "duty": "Prepare background information, outlines, and well-crafted scripts for hosts and co-hosts."
    },
    {
      "duty": "Attend producer meetings to contribute ideas, share progress, and align with the team's objectives."
    }
  ],
  "subjective_elements": [
    {
      "soldier_general": 50,
      "student_teacher": 100,
      "introvert_extrovert": 120
    }
  ],
  "education_certification": [
    {
      "credential": "Bachelor's Degree in Broadcasting, Journalism, English, Communications, or a related field (Master's preferred)"
    }
  ]
}