{
  "meta": [
    {
      "job_title": "Contract Development Analyst",
      "job_category": "Government",
      "job_class": "Analyst",
      "sector": "Government",
      "salary": 60000,
      "remote": false
    }
  ],
  "skills": [
    {
      "skill": "State Contracting Processes and Laws",
      "experience": 4
    },
    {
      "skill": "Microsoft Office Suite",
      "experience": 4
    },
    {
      "skill": "Financial Information System for California (FI$Cal)",
      "experience": 4
    },
    {
      "skill": "Analytical and Organizational Skills",
      "experience": 4
    },
    {
      "skill": "Strong Writing Skills",
      "experience": 4
    },
    {
      "skill": "Effective Communication Skills",
      "experience": 4
    },
    {
      "skill": "Procurement and Services Contracts",
      "experience": 4
    }
  ],
  "duties_responsibilities": [
    {
      "duty": "Advise and assist DTSC programs on the development, preparation, and execution of contracts, including site specific Architectural and Engineering (A&E) agreements, departmental master remediation agreements, interagency agreements, service agreements, and reimbursement agreements"
    },
    {
      "duty": "Review proposed agreements to ensure compliance with Public Contract Code, Government Code, State Contracting Manual, and Health and Safety Code"
    },
    {
      "duty": "Advise and assist DTSC programs on the development, preparation, and advertising of contract solicitations"
    }
  ],
  "subjective_elements": [
    {
      "soldier_general": 120,
      "student_teacher": 100,
      "introvert_extrovert": 80
    }
  ],
  "education_certification": [
    {
      "credential": "Bachelor's degree in Business, Public Administration, or a related field (Master's preferred)"
    }
  ]
}