{
  "meta": [
    {
      "job_title": "Content Specialist",
      "job_category": "Content",
      "job_class": "Specialist",
      "sector": "Education",
      "salary": 60000,
      "remote": true
    }
  ],
  "duties_responsibilities": [
    {
      "duty": "Responsible for daily functions of one or more handscoring contracts, including scheduling, resource planning, and developing item-specific training."
    },
    {
      "duty": "Managing a team of Scoring Directors, Supervisors, and Scorers during active scoring and performing post-project work and data analysis."
    },
    {
      "duty": "Thorough knowledge of science topics for Elementary, Middle, and High School Science and an ability to apply state and national science standards."
    },
    {
      "duty": "Clear communication to a variety of roles daily, both in person and virtually, and the ability to work in a team environment."
    },
    {
      "duty": "Mentoring and training Scoring Directors, Supervisors, and Scorers in the expectations of each of those roles and how to perform those duties."
    }
  ],
  "skills": [
    {
      "skill": "Science Expertise",
      "experience": 2
    },
    {
      "skill": "Item Development",
      "experience": 2
    },
    {
      "skill": "Data Analysis",
      "experience": 3
    },
    {
      "skill": "Clear Communication",
      "experience": 4
    },
    {
      "skill": "Training and Coaching",
      "experience": 4
    },
    {
      "skill": "Science Education",
      "experience": 2
    },
    {
      "skill": "Math Assessment",
      "experience": 3
    },
    {
      "skill": "Science Assessment",
      "experience": 3
    },
    {
      "skill": "Customer Liaison",
      "experience": 3
    }
  ],
  "subjective_elements": [
    {
      "soldier_general": 100,
      "student_teacher": 120,
      "introvert_extrovert": 80
    }
  ],
  "education_certification": [
    {
      "credential": "Bachelor\u2019s degree in Life Science or Physical Sciences (Additional Math college courses preferred)"
    },
    {
      "credential": "Two (2) years assessment industry experience as a Scoring Director or other scoring team lead or equivalent experience"
    }
  ]
}