{
  "meta": [
    {
      "job_title": "Director, Biostatistics",
      "job_category": "Biostatistics",
      "job_class": "Director",
      "sector": "Pharmaceutical",
      "salary": 180000,
      "remote": false
    }
  ],
  "skills": [
    {
      "skill": "Biostatistics",
      "experience": 10
    },
    {
      "skill": "Statistical Methodology",
      "experience": 10
    },
    {
      "skill": "Data Analysis",
      "experience": 10
    },
    {
      "skill": "Clinical Trial Design",
      "experience": 10
    },
    {
      "skill": "SAS Programming",
      "experience": 10
    },
    {
      "skill": "R Programming",
      "experience": 10
    },
    {
      "skill": "Communication Skills",
      "experience": 10
    },
    {
      "skill": "Leadership",
      "experience": 10
    }
  ],
  "duties_responsibilities": [
    {
      "duty": "Lead the biostatistics activities for key development programs"
    },
    {
      "duty": "Develop and execute statistical strategy, design, and analyses for clinical trials"
    },
    {
      "duty": "Review/input eCRFs, SDTM specifications, ADaM specifications and statistical algorithms; review ADaM datasets; participate in data review and data cleaning activities."
    },
    {
      "duty": "SAS and R programming for efficacy analyses and statistical modeling"
    },
    {
      "duty": "Interact frequently and effectively with members of the biometrics and clinical organization to develop, revise, implement and supervise statistical strategies for ongoing and planned clinical study activities"
    },
    {
      "duty": "Help design data capture methods and select appropriate study endpoints for clinical programs"
    },
    {
      "duty": "Attend meetings with regulatory agencies and support/defend clinical programs"
    },
    {
      "duty": "Be able to conduct independent research and resolve statistical methodological issues"
    },
    {
      "duty": "Oversee statistical vendors\u2019 tasks and be accountable for the timely and high-quality biostatistics deliverables"
    }
  ],
  "subjective_elements": [
    {
      "soldier_general": 80,
      "student_teacher": 140,
      "introvert_extrovert": 160
    }
  ],
  "education_certification": [
    {
      "credential": "PhD in biotech or pharmaceutical companies with 8+ years of experience or Master with 10+ years of experience"
    }
  ]
}