{
  "meta": [
    {
      "job_title": "Truck Driver",
      "job_category": "Transportation",
      "job_class": "Driver",
      "sector": "Logistics",
      "salary": 44000,
      "remote": false
    }
  ],
  "duties_responsibilities": [
    {
      "duty": "Drive a spotter truck and/or day cab within the distribution center from and to loading doors."
    },
    {
      "duty": "Shuttle trailers over public road."
    },
    {
      "duty": "Hold a non-excepted interstate status on their medical card."
    },
    {
      "duty": "Hold a valid CDL-A and Medical Card."
    },
    {
      "duty": "Work in a timely & safely manner."
    },
    {
      "duty": "Communicate professionally and diplomatically."
    }
  ],
  "skills": [],
  "subjective_elements": [],
  "education_certification": []
}