{
  "meta": [
    {
      "job_title": "Consultant, Environmental Scientist",
      "job_category": "Environmental Science",
      "job_class": "Consultant",
      "sector": "Environmental Science",
      "salary": 85000,
      "remote": true
    }
  ],
  "skills": [
    {
      "skill": "Environmental Science",
      "experience": 3
    },
    {
      "skill": "Project Management",
      "experience": 2
    },
    {
      "skill": "Technical Analysis",
      "experience": 2
    },
    {
      "skill": "Field Surveys",
      "experience": 3
    },
    {
      "skill": "Client Interaction",
      "experience": 3
    },
    {
      "skill": "Report Writing",
      "experience": 3
    },
    {
      "skill": "Health & Safety Protocols",
      "experience": 3
    },
    {
      "skill": "Data Analysis",
      "experience": 3
    },
    {
      "skill": "Verbal Communication",
      "experience": 3
    },
    {
      "skill": "Written Communication",
      "experience": 3
    },
    {
      "skill": "Organizational Skills",
      "experience": 3
    },
    {
      "skill": "Research",
      "experience": 2
    },
    {
      "skill": "Consulting",
      "experience": 3
    }
  ],
  "duties_responsibilities": [
    {
      "duty": "Provide creative and fit-for-purpose technical analyses and support additional analyses for other areas of specialization"
    },
    {
      "duty": "Support the growth of service offerings for energy sector clients and conduct desktop research on environmental constraints and permitting processes"
    },
    {
      "duty": "Interact directly with clients and their SMEs on matters related to biology and environmental science"
    },
    {
      "duty": "Work within quality/budget/schedule expectations and scope-specific assignments"
    },
    {
      "duty": "Complete work assignments in accordance with ERM's management system, format, and quality standards"
    }
  ],
  "subjective_elements": [
    {
      "soldier_general": 60,
      "student_teacher": 40,
      "introvert_extrovert": 130
    }
  ],
  "education_certification": [
    {
      "credential": "Bachelors and/or Masters degree in environmental science/engineering, biology/ecology, planning, or natural science discipline"
    }
  ]
}