{
  "meta": [
    {
      "job_title": "Account Manager",
      "job_category": "Sales",
      "job_class": "Manager",
      "sector": "Sales",
      "salary": 200000,
      "remote": false
    }
  ],
  "skills": [
    {
      "skill": "Client Communication",
      "experience": 10
    },
    {
      "skill": "Team Leadership",
      "experience": 8
    },
    {
      "skill": "Market Strategy Development",
      "experience": 8
    },
    {
      "skill": "Presentation Skills",
      "experience": 8
    },
    {
      "skill": "Relationship Management",
      "experience": 8
    },
    {
      "skill": "Business Development",
      "experience": 8
    },
    {
      "skill": "Account Management",
      "experience": 8
    },
    {
      "skill": "Marketing Strategy",
      "experience": 8
    },
    {
      "skill": "Client Service",
      "experience": 8
    },
    {
      "skill": "Sales Management",
      "experience": 8
    },
    {
      "skill": "Microsoft Office",
      "experience": 5
    },
    {
      "skill": "Agency Management System (EPIC)",
      "experience": 5
    },
    {
      "skill": "Marketing Strategy",
      "experience": 10
    },
    {
      "skill": "Microsoft Office",
      "experience": 8
    },
    {
      "skill": "Property and Casualty Insurance",
      "experience": 8
    }
  ],
  "duties_responsibilities": [
    {
      "duty": "Cultivates and maintains professional and proactive communication level with clients, production staff, and other associates."
    },
    {
      "duty": "Manages, leads, and develops direct reports, including Account Executives, and has ultimate responsibility of service teams within a specified industry."
    },
    {
      "duty": "Monitors and coordinates: training and development of all service team members, assigns new accounts and transfers of accounts among staff to maintain workable workloads, ensures quality control standards of the team are continually maintained."
    },
    {
      "duty": "Develops marketing strategy for new and renewal business and prepares, submits, and negotiates new and renewal marketing to insurance carriers."
    },
    {
      "duty": "Develops a service plan tailored to client\u2019s needs and coordinates the services of other departments."
    },
    {
      "duty": "Prepares and leads internal and client-facing business reviews to ensure level of service and adequacy of client\u2019s program design based on their business needs and risk tolerance."
    },
    {
      "duty": "Participates in industry-specific associations and networking events to cultivate relationships within the industry and expand the brand."
    },
    {
      "duty": "Supports the department by participating in completion of all duties required to complete a project and service a client."
    },
    {
      "duty": "Serves as a leadership champion of organizational initiatives."
    },
    {
      "duty": "Communicates with market president regarding department strategies, needs, and performance."
    }
  ],
  "subjective_elements": [
    {
      "soldier_general": 150
    },
    {
      "student_teacher": 100
    },
    {
      "introvert_extrovert": 120
    }
  ],
  "education_certification": [
    {
      "credential": "Bachelor\u2019s degree preferred or equivalent experience."
    }
  ]
}