{
  "meta": [
    {
      "job_title": "Commercial Alarm and Security Installer",
      "job_category": "Installation & Technical Support",
      "job_class": "Technician",
      "sector": "Security",
      "salary": 50000,
      "remote": true
    }
  ],
  "duties_responsibilities": [
    {
      "duty": "Installs commercial alarm, fire, CCTV, and Card Access systems."
    },
    {
      "duty": "Proctors, coaches, and teaches others."
    },
    {
      "duty": "Provides reliable, high quality customer support."
    },
    {
      "duty": "Performs customer instruction on system operation and functionality."
    },
    {
      "duty": "Performs system testing and signal verification."
    },
    {
      "duty": "Maintains the necessary truck stock/inventory (equipment and tools)."
    },
    {
      "duty": "Organizes and utilizes technical resources, information, material, and support to ensure efficient execution of assigned tasks."
    },
    {
      "duty": "Monitors and ensures the progress and completion of assigned tasks."
    },
    {
      "duty": "Completes and submits all required task-related activities, productivity, and other documentation in a timely manner."
    },
    {
      "duty": "Must have a strong work ethic."
    },
    {
      "duty": "Must be detail-oriented."
    },
    {
      "duty": "Completes other projects, as assigned."
    }
  ],
  "skills": [
    {
      "skill": "Commercial Alarm Installation",
      "experience": 3
    },
    {
      "skill": "Fire Alarm Systems",
      "experience": 3
    },
    {
      "skill": "CCTV Systems",
      "experience": 3
    },
    {
      "skill": "Access Control Systems",
      "experience": 3
    },
    {
      "skill": "Customer Support",
      "experience": 3
    },
    {
      "skill": "Troubleshooting",
      "experience": 3
    }
  ],
  "subjective_elements": [
    {
      "soldier_general": 100
    },
    {
      "student_teacher": 80
    },
    {
      "introvert_extrovert": 60
    }
  ],
  "education_certification": [
    {
      "credential": "High School Diploma/Vocational Training"
    },
    {
      "credential": "Valid driver\u2019s license"
    },
    {
      "credential": "Product certifications and/or licenses as required by national, state, and local codes"
    }
  ]
}