{
  "meta": [
    {
      "job_title": "CLEAR Sports Ambassador",
      "job_category": "Sports and Entertainment",
      "job_class": "Ambassador",
      "sector": "Hospitality",
      "salary": 19.0,
      "remote": false
    }
  ],
  "skills": [
    {
      "skill": "Autonomy",
      "experience": 3
    },
    {
      "skill": "Communication Skills",
      "experience": 5
    },
    {
      "skill": "Engagement",
      "experience": 4
    },
    {
      "skill": "Customer Service",
      "experience": 5
    },
    {
      "skill": "Hospitality Experience",
      "experience": 4
    },
    {
      "skill": "Retail Experience",
      "experience": 4
    },
    {
      "skill": "Event Management",
      "experience": 4
    },
    {
      "skill": "Flexible Schedule",
      "experience": 4
    },
    {
      "skill": "Security Compliance",
      "experience": 4
    },
    {
      "skill": "Problem Solving",
      "experience": 4
    }
  ],
  "duties_responsibilities": [
    {
      "duty": "Function autonomously and with integrity to verify current members at sports and entertainment venues."
    },
    {
      "duty": "Engage with potential customers and members, follow detailed instructions, and execute them with 100% accuracy in a fast-paced and constantly changing environment."
    },
    {
      "duty": "Drive membership enrollments through engaging fans and educating them about the benefits of CLEAR."
    },
    {
      "duty": "Balancing high volume with high-quality customer experiences and resolving fan and/or members concerns or inquiries in a timely manner."
    }
  ],
  "subjective_elements": [
    {
      "soldier_general": 150,
      "student_teacher": 100,
      "introvert_extrovert": 80
    }
  ],
  "education_certification": [
    {
      "credential": "18 years of age or older, and previous hospitality, events and/or retail experience"
    }
  ]
}