{
  "meta": [
    {
      "job_title": "Project Management Support Supervisor",
      "job_category": "Project Management",
      "job_class": "Supervisor",
      "sector": "Management",
      "salary": 82000,
      "remote": true
    }
  ],
  "skills": [
    {
      "skill": "Analytical Support",
      "experience": 4
    },
    {
      "skill": "Project Management",
      "experience": 5
    },
    {
      "skill": "Vendor Management",
      "experience": 4
    },
    {
      "skill": "Training Development",
      "experience": 3
    },
    {
      "skill": "Microsoft Office Applications",
      "experience": 5
    },
    {
      "skill": "Data Analysis",
      "experience": 4
    },
    {
      "skill": "Management",
      "experience": 5
    },
    {
      "skill": "Leadership",
      "experience": 5
    },
    {
      "skill": "Travel Coordination",
      "experience": 5
    },
    {
      "skill": "Communication",
      "experience": 5
    },
    {
      "skill": "Problem Solving",
      "experience": 5
    },
    {
      "skill": "Supervision",
      "experience": 5
    }
  ],
  "duties_responsibilities": [
    {
      "duty": "Provide analytical support of line operations throughout all production facilities"
    }
  ],
  "subjective_elements": [
    {
      "soldier_general": 100,
      "student_teacher": 70,
      "introvert_extrovert": 50
    }
  ],
  "education_certification": [
    {
      "credential": "Bachelor's Degree in Business Administration or other related field (Master's preferred)"
    }
  ]
}