{
  "meta": [
    {
      "job_title": "Project Design Engineer",
      "job_category": "Engineering",
      "job_class": "Engineer",
      "sector": "Automotive",
      "salary": 85000,
      "remote": false
    }
  ],
  "skills": [
    {
      "skill": "Structural Calculations",
      "experience": 5
    },
    {
      "skill": "Project Management",
      "experience": 5
    },
    {
      "skill": "AutoCAD",
      "experience": 5
    },
    {
      "skill": "Technical Problem-Solving",
      "experience": 5
    },
    {
      "skill": "Engineering Design",
      "experience": 5
    },
    {
      "skill": "Communication Skills",
      "experience": 5
    },
    {
      "skill": "Field Inspection",
      "experience": 5
    },
    {
      "skill": "Team Collaboration",
      "experience": 5
    },
    {
      "skill": "Planning and Scheduling",
      "experience": 5
    },
    {
      "skill": "Data Analysis",
      "experience": 5
    }
  ],
  "duties_responsibilities": [
    {
      "duty": "Overseeing all engineering and technical aspects of assigned projects to assure accuracy and quality."
    },
    {
      "duty": "Supporting structural calculations and state-certified drawings."
    },
    {
      "duty": "Performing engineering calculations and providing ABM's and Work Orders."
    },
    {
      "duty": "Developing technical solutions to issues in a timely manner and providing AutoCAD conveyor layouts."
    },
    {
      "duty": "Reviewing and tracking project requirements, visiting job sites, and providing start-up assistance as required."
    },
    {
      "duty": "Training and monitoring engineering sub-contractors selected for the project."
    }
  ],
  "subjective_elements": [
    {
      "soldier_general": 100,
      "student_teacher": 80,
      "introvert_extrovert": 120
    }
  ],
  "education_certification": [
    {
      "credential": "Bachelor\u2019s degree in mechanical engineering and 5 plus years of automotive conveyor work experience, or a non-degreed with 5 plus years\u2019 experience in automotive conveyor work."
    }
  ]
}