{
  "meta": [
    {
      "job_title": "Retail Team Lead",
      "job_category": "Sales",
      "job_class": "Team Lead",
      "sector": "Sales",
      "salary": 45000,
      "remote": false
    }
  ],
  "skills": [
    {
      "skill": "Retail Management",
      "experience": 5
    },
    {
      "skill": "Team Leadership",
      "experience": 5
    },
    {
      "skill": "Customer Service",
      "experience": 5
    },
    {
      "skill": "Retail Operations",
      "experience": 5
    },
    {
      "skill": "Communication Skills",
      "experience": 5
    },
    {
      "skill": "Adaptability",
      "experience": 5
    },
    {
      "skill": "Omni Channel Service",
      "experience": 5
    }
  ],
  "duties_responsibilities": [
    {
      "duty": "Execute best in class sales and service strategies to reinforce exceptional customer service behaviors delivered by the store team."
    },
    {
      "duty": "Deliver a customer-friendly in-store and curbside shopping experience by leveraging technology to enhance the customer service experience."
    },
    {
      "duty": "Help deliver on sales, profit, and service targets, as well as deliver on key Omni strategies and metrics."
    },
    {
      "duty": "Master all Omni channel service platforms, including in-store pickup, delivery, curbside pickup, and others."
    },
    {
      "duty": "Manage and plan the daily and weekly workload to deliver on store sales goals and customer engagement."
    },
    {
      "duty": "Assist the Store Team Leader with team onboarding and learning, and continuously direct and coach store team members."
    },
    {
      "duty": "Work a schedule that aligns to customer and business needs, including early morning, evening, overnight shifts, and weekends."
    },
    {
      "duty": "Create an environment that promotes associate engagement and retention as part of the Leader on Duty (LOD) team."
    }
  ],
  "subjective_elements": [
    {
      "soldier_general": 100,
      "student_teacher": 80,
      "introvert_extrovert": 100
    }
  ],
  "education_certification": [
    {
      "credential": "Prior retail management experience"
    }
  ]
}