{
  "meta": [
    {
      "job_title": "Senior Internal Auditor",
      "job_category": "Accounting",
      "job_class": "Senior Auditor",
      "sector": "Finance",
      "salary": 95000,
      "remote": false
    }
  ],
  "duties_responsibilities": [
    {
      "duty": "Review and evaluate risks and the effectiveness of the internal control environment; and analyze business processes to make suggestions for improvement."
    },
    {
      "duty": "Perform SOX compliance, transactional, and operational testing across all processes."
    },
    {
      "duty": "Help implement solutions to control weaknesses."
    },
    {
      "duty": "Analyze and evaluate data for compliance with laws, corporate policies and procedures, and best business practices."
    },
    {
      "duty": "Act as a key point person and leader for teams in the field."
    },
    {
      "duty": "Lead and perform advisory and related client service activities."
    },
    {
      "duty": "Participate in the completion of quarter-end, interim, and year-end audit procedures to assist External Auditors."
    },
    {
      "duty": "Assist with the completion of financial/operational audits."
    },
    {
      "duty": "Complete Special Projects as assigned by the Vice President, Internal Audit & Compliance."
    },
    {
      "duty": "Participate in Physical Inventories of raw materials, finished goods, and parts."
    },
    {
      "duty": "Create professional reports and assist with presentations as needed."
    },
    {
      "duty": "Team with clients to identify and solve problems."
    },
    {
      "duty": "Willingness to travel in the 25% range."
    },
    {
      "duty": "Other duties as assigned."
    }
  ],
  "skills": [
    {
      "skill": "Internal Audit",
      "experience": 2
    },
    {
      "skill": "Compliance",
      "experience": 2
    },
    {
      "skill": "Accounting",
      "experience": 2
    },
    {
      "skill": "Project Management",
      "experience": 2
    },
    {
      "skill": "Microsoft Office",
      "experience": 2
    },
    {
      "skill": "SAP or ERP Systems",
      "experience": 2
    },
    {
      "skill": "Communication Skills",
      "experience": 2
    },
    {
      "skill": "Analytical Skills",
      "experience": 2
    },
    {
      "skill": "Team Leadership",
      "experience": 2
    }
  ],
  "subjective_elements": [
    {
      "soldier_general": 100,
      "student_teacher": 80,
      "introvert_extrovert": 100
    }
  ],
  "education_certification": [
    {
      "credential": "Bachelor\u2019s Degree (Preferred Major: Accounting, Finance or another related field)"
    },
    {
      "credential": "CIA, CISA, or CPA preferred (or willingness to attain)"
    }
  ]
}