{
  "meta": [
    {
      "job_title": "Directeur adjoint de succursale",
      "job_category": "Management",
      "job_class": "Assistant Manager",
      "sector": "Sales",
      "salary": 50000,
      "remote": false
    }
  ],
  "skills": [
    {
      "skill": "Gestion du march\u00e9",
      "experience": 3
    },
    {
      "skill": "Service \u00e0 la client\u00e8le",
      "experience": 3
    },
    {
      "skill": "Gestion des stocks",
      "experience": 3
    },
    {
      "skill": "Gestion des op\u00e9rations",
      "experience": 3
    },
    {
      "skill": "Gestion financi\u00e8re",
      "experience": 3
    },
    {
      "skill": "Recrutement et planification du personnel",
      "experience": 3
    },
    {
      "skill": "Comp\u00e9tences en communication",
      "experience": 3
    },
    {
      "skill": "Leadership d'\u00e9quipe",
      "experience": 3
    }
  ],
  "duties_responsibilities": [
    {
      "duty": "Contribuer \u00e0 l\u2019\u00e9laboration et \u00e0 la mise en \u0153uvre du plan de march\u00e9 de la succursale en fonction des conditions du march\u00e9, de la mission de la succursale et des objectifs financiers/budg\u00e9taires."
    },
    {
      "duty": "V\u00e9rifier que toutes les transactions sont trait\u00e9es correctement par le syst\u00e8me d\u2019exploitation informatique de la succursale."
    },
    {
      "duty": "S\u2019assurer que les clients sont servis de mani\u00e8re appropri\u00e9e et professionnelle en r\u00e9pondant \u00e0 leurs questions et \u00e0 leurs plaintes. "
    },
    {
      "duty": "S\u2019assurer que toutes les commandes des clients sont pr\u00e9par\u00e9es avec pr\u00e9cision et que les dossiers sont conserv\u00e9s."
    },
    {
      "duty": "Maintenir les niveaux d\u2019inventaire de la succursale pour maximiser les ventes et la rotation des stocks."
    },
    {
      "duty": "Respecter les normes de s\u00e9curit\u00e9 de l\u2019entreprise, les pratiques de pr\u00e9vention des pertes et de s\u00e9curit\u00e9; confirmer qu\u2019elles sont suivies par tous les employ\u00e9s de la succursale conform\u00e9ment \u00e0 la politique; corriger ou signaler les cas de non-conformit\u00e9."
    },
    {
      "duty": "Aider \u00e0 effectuer les d\u00e9p\u00f4ts bancaires quotidiens."
    },
    {
      "duty": "Examiner fr\u00e9quemment les rapports de gestion/financiers afin d\u2019optimiser les performances financi\u00e8res de la succursale."
    },
    {
      "duty": "D\u00e9terminer les besoins en personnel, recruter les employ\u00e9s de la succursale en cons\u00e9quence avec l\u2019approbation appropri\u00e9e, et \u00e9tablir les horaires de travail correspondants."
    },
    {
      "duty": "Effectuer des calculs math\u00e9matiques de base et des ratios financiers relatifs aux profits et pertes."
    },
    {
      "duty": "Prendre des d\u00e9cisions de mani\u00e8re autonome."
    }
  ],
  "subjective_elements": [
    {
      "soldier_general": 100,
      "student_teacher": 60,
      "introvert_extrovert": 90
    }
  ],
  "education_certification": [
    {
      "credential": "Dipl\u00f4me d\u2019\u00e9tudes secondaires ou l\u2019\u00e9quivalent."
    }
  ]
}